{
  "db_name": "PostgreSQL",
  "query": "SELECT id, shop_id, user_id, status, message, response_message, created_at, updated_at\n                 FROM shop_subscriptions\n                 WHERE shop_id = $1 AND status = $2\n                 ORDER BY created_at DESC",
  "describe": {
    "columns": [
      {
        "ordinal": 0,
        "name": "id",
        "type_info": "Int4"
      },
      {
        "ordinal": 1,
        "name": "shop_id",
        "type_info": "Int4"
      },
      {
        "ordinal": 2,
        "name": "user_id",
        "type_info": "Int4"
      },
      {
        "ordinal": 3,
        "name": "status",
        "type_info": "Varchar"
      },
      {
        "ordinal": 4,
        "name": "message",
        "type_info": "Text"
      },
      {
        "ordinal": 5,
        "name": "response_message",
        "type_info": "Text"
      },
      {
        "ordinal": 6,
        "name": "created_at",
        "type_info": "Timestamptz"
      },
      {
        "ordinal": 7,
        "name": "updated_at",
        "type_info": "Timestamptz"
      }
    ],
    "parameters": {
      "Left": [
        "Int4",
        "Text"
      ]
    },
    "nullable": [
      false,
      false,
      false,
      false,
      true,
      true,
      false,
      false
    ]
  },
  "hash": "cf1e8663fa8daa73283ba8ffa0ef8538730bacce9568feb672893dd3edc07241"
}
